{"order":["main-collection-banner","main-collection-product-grid"],"sections":{"main-collection-banner":{"settings":{"color_scheme":"scheme-1","show_collection_description":true,"show_collection_image":true},"type":"main-collection-banner"},"main-collection-product-grid":{"settings":{"color_scheme":"scheme-1","columns_desktop":4,"columns_mobile":"2","enable_filtering":true,"enable_sorting":true,"filter_type":"horizontal","image_ratio":"adapt","image_shape":"default","padding_bottom":68,"padding_top":0,"products_per_page":20,"quick_add":"none","show_rating":false,"show_secondary_image":true,"show_vendor":false},"type":"main-collection-product-grid"}}}